BlyncsySFT/__init__.py
BlyncsySFT/__main__.py
BlyncsySFT/augment.py
BlyncsySFT/cli.py
BlyncsySFT/config.py
BlyncsySFT/eval.py
BlyncsySFT/format.py
BlyncsySFT/models.py
BlyncsySFT/pipeline.py
BlyncsySFT/postprocess.py
BlyncsySFT/preprocessing.py
BlyncsySFT/saliency.py
blyncsysft-0.1.2.dist-info/licenses/LICENSE
blyncsysft-0.1.2.dist-info/METADATA
blyncsysft-0.1.2.dist-info/WHEEL
blyncsysft-0.1.2.dist-info/entry_points.txt
blyncsysft-0.1.2.dist-info/top_level.txt
blyncsysft-0.1.2.dist-info/RECORD
