Metadata-Version: 2.4
Name: BlyncsySFT
Version: 0.1.2
Summary: Supervised Fine-Tuning Package for Blyncsy
Author-email: Sonny Jones <sonny.jones@utah.edu>, Anthony Le <anthony.le@utah.edu>, Rohit Raj <rohitrraj284@gmail.com>
Maintainer-email: Sonny Jones <sonny.jones@utah.edu>
Classifier: Programming Language :: Python :: 3
Classifier: Intended Audience :: Science/Research
Classifier: License :: OSI Approved :: MIT License
Classifier: Operating System :: OS Independent
Requires-Python: >=3.6
License-File: LICENSE
Requires-Dist: torch>=2.6.0
Requires-Dist: torchvision>=0.15.0
Requires-Dist: numpy>=1.21.0
Requires-Dist: tqdm>=4.67.1
Requires-Dist: pycocotools>=2.0.8
Requires-Dist: opencv-python>=4.11.0.86
Requires-Dist: click>=8.1.3
Requires-Dist: PyYAML>=6.0
Requires-Dist: scikit-learn>=0.23.2
Requires-Dist: python-dotenv>=1.1.0
Requires-Dist: albumentations>=2.0.5
Requires-Dist: pillow>=9.0.1
Requires-Dist: matplotlib>=3.7.1
Dynamic: license-file
